AUTHORS.rst
CHANGELOG.rst
LICENSE
MANIFEST.in
README.rst
setup.py
composer/__init__.py
composer/admin.py
composer/apps.py
composer/context_processors.py
composer/managers.py
composer/middleware.py
composer/models.py
composer/utils.py
composer/views.py
composer/migrations/0001_initial.py
composer/migrations/0002_auto_20170126_0518.py
composer/migrations/__init__.py
composer/templates/composer/slot_detail.html
composer/templates/composer/inclusion_tags/composer.html
composer/templates/composer/inclusion_tags/tile.html
composer/templatetags/__init__.py
composer/templatetags/composer_tags.py
composer/tests/__init__.py
composer/tests/manage.py
composer/tests/models.py
composer/tests/test_admin.py
composer/tests/test_middleware.py
composer/tests/test_templatetags.py
composer/tests/urls.py
composer/tests/views.py
composer/tests/additionals/__init__.py
composer/tests/additionals/templates/composer/inclusion_tags/tile_context.html
composer/tests/additionals/templates/tests/inclusion_tags/dummymodel2_3rdparty_override.html
composer/tests/requirements/111.txt
composer/tests/requirements/19.txt
composer/tests/settings/111.py
composer/tests/settings/19.py
composer/tests/settings/__init__.py
composer/tests/templates/base.html
composer/tests/templates/composer/inclusion_tags/content.html
composer/tests/templates/composer/inclusion_tags/default_slot_context.html
composer/tests/templates/composer/inclusion_tags/tile.html
composer/tests/templates/tests/aaa.html
composer/tests/templates/tests/bbb.html
composer/tests/templates/tests/dummymodel1_detail.html
composer/tests/templates/tests/header.html
composer/tests/templates/tests/home.html
composer/tests/templates/tests/slot_context.html
composer/tests/templates/tests/inclusion_tags/dummymodel1_style_for_model_one.html
composer/tests/templates/tests/inclusion_tags/dummymodel2_extra_style.html
composer/tests/templates/tests/inclusion_tags/dummymodel2_tile.html
django_composer_prk.egg-info/PKG-INFO
django_composer_prk.egg-info/SOURCES.txt
django_composer_prk.egg-info/dependency_links.txt
django_composer_prk.egg-info/not-zip-safe
django_composer_prk.egg-info/requires.txt
django_composer_prk.egg-info/top_level.txt