Metadata-Version: 1.1
Name: django-composer-prk
Version: 0.1.1
Summary: Page composer for Django
Home-page: https://github.com/praekelt/django-composer-prk
Author: Praekelt Consulting
Author-email: dev@praekelt.com
License: BSD
Platform: UNKNOWN
Classifier: Programming Language :: Python
Classifier: License :: OSI Approved :: BSD License
Classifier: Development Status :: 5 - Production/Stable
Classifier: Operating System :: OS Independent
Classifier: Framework :: Django
Classifier: Intended Audience :: Developers
Classifier: Topic :: Internet :: WWW/HTTP :: Dynamic Content
